__init__.py
shplat.py
shplat-0.0.1.dist-info/METADATA
shplat-0.0.1.dist-info/WHEEL
shplat-0.0.1.dist-info/entry_points.txt
shplat-0.0.1.dist-info/top_level.txt
shplat-0.0.1.dist-info/RECORD
